{
"type": "FeatureCollection",
"name": "AGENTE_CARLOS_ALBERTO_DE_CAMPOS_PIRES",
"crs": { "type": "name", "properties": { "name": "urn:ogc:def:crs:OGC:1.3:CRS84" } },
"xy_coordinate_resolution": 1e-15,
"features": [
{ "type": "Feature", "properties": { "CNPJ": 47170096000108, "AGENTE": "CARLOS_ALBERTO_DE_CAMPOS_PIRES", "ACAO": "REALIZAR_SEGUNDA_VISITA", "RAZAO_SOCIAL": "MS_PRODUTOS", "ENDERECO": "RUA_JACUTINGA_1026_JARDIM_OLINDA_RIO_CLARO_BRASIL", "CIDADE": "RIO_CLARO", "LATITUDE": -22.3924861, "LONGITUDE": -47.5795684, "LMAPS": "https://www.google.com/maps/@?api=1&map_action=pano&viewpoint=--22.3924861,-47.5795684" }, "geometry": { "type": "Point", "coordinates": [ -47.5795684, -22.3924861 ] } }
]
}
