{
"type": "FeatureCollection",
"name": "GABRIEL_ALVES_DOS_SANTOS",
"crs": { "type": "name", "properties": { "name": "urn:ogc:def:crs:OGC:1.3:CRS84" } },
"xy_coordinate_resolution": 1e-15,
"features": [
{ "type": "Feature", "properties": { "CNPJ": 52678519000127, "AGENTE": "GABRIEL_ALVES_DOS_SANTOS", "ACAO": "REALIZAR_SEGUNDA_VISITA", "RAZAO_SOCIAL": "LOJAS_POP_15_LTDA_-_LOJAS_POP_20", "ENDERECO": "RUAITIRAPINA_1485_CIDADELUIZA_JUNDIAI", "CIDADE": "JUNDIAI", "LATITUDE": -23.1682341, "LONGITUDE": -46.9100304, "BASE": "ATENDIDOS" }, "geometry": { "type": "Point", "coordinates": [ -46.9100304, -23.1682341 ] } }
]
}
